mltz_base/__init__.py
mltz_base/eda.py
mltz_base/numbers.py
mltz_base-0.1.26.dist-info/METADATA
mltz_base-0.1.26.dist-info/LICENSE
mltz_base-0.1.26.dist-info/WHEEL
mltz_base-0.1.26.dist-info/RECORD
