Metadata-Version: 2.1
Name: mltz-base
Version: 0.1.26
Summary: Base Package for ML related dev
License: MIT
Author: Tony Zoght
Requires-Python: >=3.9
Classifier: License :: OSI Approved :: MIT License
Classifier: Programming Language :: Python :: 3
Classifier: Programming Language :: Python :: 3.9
Classifier: Programming Language :: Python :: 3.10
Classifier: Programming Language :: Python :: 3.11
Requires-Dist: numpy (>=1.24.0)
Requires-Dist: pandas (>=1.4.0)
